esok/__init__.py
esok/constants.py
esok/esok.py
esok/init.py
esok/util.py
esok/commands/__init__.py
esok/commands/alias.py
esok/commands/config.py
esok/commands/index.py
esok/commands/reindex.py
esok/config/__init__.py
esok/config/config.py
esok/config/connection_options.py
esok/log/ConsoleFormatter.py
esok/log/ConsoleHandler.py
esok/log/LogLevelFilter.py
esok/log/__init__.py
esok/log/decorator.py
esok/resources/esok.ini
esok/resources/logging.yaml
esok-0.1.0.dist-info/LICENSE
esok-0.1.0.dist-info/METADATA
esok-0.1.0.dist-info/WHEEL
esok-0.1.0.dist-info/entry_points.txt
esok-0.1.0.dist-info/top_level.txt
esok-0.1.0.dist-info/RECORD
