Metadata-Version: 2.1
Name: esok
Version: 0.1.0
Summary: A CLI for Elasticsearch
Home-page: https://github.com/ahaeger/esok
Author: Alexander Häger
Author-email: me@haeger.me
Maintainer: Alexander Häger
Maintainer-email: me@haeger.me
License: MIT
Keywords: elasticsearch,es,cli
Platform: UNKNOWN
Classifier: Development Status :: 4 - Beta
Classifier: Intended Audience :: Developers
Classifier: Intended Audience :: System Administrators
Classifier: Natural Language :: English
Classifier: Environment :: Console
Classifier: License :: OSI Approved :: MIT License
Classifier: Operating System :: OS Independent
Classifier: Programming Language :: Python
Classifier: Programming Language :: Python :: 3
Classifier: Programming Language :: Python :: 3.6
Classifier: Programming Language :: Python :: 3.7
Classifier: Programming Language :: Python :: 3.8
Classifier: Topic :: Utilities
License-File: LICENSE
Requires-Dist: click (<8,>=7.1.2)
Requires-Dist: click-didyoumean (<1,>=0.0.3)
Requires-Dist: elasticsearch (<7,>=6.8.1)
Requires-Dist: PyYAML (<6,>=5.1.0)
